letsreadscraper/__init__.py
letsreadscraper/scraper.py
letsreadscraper/utilities.py
letsreadscraper-0.1.4.dist-info/METADATA
letsreadscraper-0.1.4.dist-info/WHEEL
letsreadscraper-0.1.4.dist-info/RECORD
