Metadata-Version: 2.1
Name: letsreadscraper
Version: 0.1.4
Summary: Python package to scrape Let's Read Website
License: MIT
Author: Mohit Shrestha
Author-email: contact@mohitshrestha.com.np
Requires-Python: >=3.12,<4.0
Classifier: License :: OSI Approved :: MIT License
Classifier: Programming Language :: Python :: 3
Classifier: Programming Language :: Python :: 3.12
Requires-Dist: chardet (>=5.2.0,<6.0.0)
Requires-Dist: jsons (>=1.6.3,<2.0.0)
Requires-Dist: pandas (>=2.2.1,<3.0.0)
Requires-Dist: requests (>=2.31.0,<3.0.0)
